srt_file_translator/__init__.py
srt_file_translator/translator.py
srt_file_translator-1.2.0.dist-info/LICENSE
srt_file_translator-1.2.0.dist-info/METADATA
srt_file_translator-1.2.0.dist-info/WHEEL
srt_file_translator-1.2.0.dist-info/top_level.txt
srt_file_translator-1.2.0.dist-info/RECORD
