Metadata-Version: 2.2
Name: srt_file_translator
Version: 1.2.0
Summary: A python translator for srt files.
Author-email: Connor Makowski <conmak@mit.edu>
Project-URL: Homepage, https://github.com/connor-makowski/srt_file_translator
Project-URL: Bug Tracker, https://github.com/connor-makowski/srt_file_translator/issues
Project-URL: Documentation, https://connor-makowski.github.io/srt_file_translator/srt_file_translator/enforcer.html
Classifier: Programming Language :: Python :: 3
Classifier: License :: OSI Approved :: MIT License
Classifier: Operating System :: OS Independent
Requires-Python: >=3.10
License-File: LICENSE
Requires-Dist: google-cloud-translate==3.19.0
Requires-Dist: type_enforced>=1.10.1
